{
  "history": [
    {
      "time": "2026-02-27T03:09:11.929502+09:00",
      "usdt_kimp": 1.3831,
      "gold_kimp": 0.2289
    },
    {
      "time": "2026-02-27T04:11:02.850186+09:00",
      "usdt_kimp": 1.313,
      "gold_kimp": -0.19
    },
    {
      "time": "2026-02-27T04:55:00.894919+09:00",
      "usdt_kimp": 1.1729,
      "gold_kimp": -0.2444
    },
    {
      "time": "2026-02-27T05:39:09.893249+09:00",
      "usdt_kimp": 1.313,
      "gold_kimp": -0.4324
    },
    {
      "time": "2026-02-27T06:19:21.431773+09:00",
      "usdt_kimp": 1.4531,
      "gold_kimp": -0.3491
    },
    {
      "time": "2026-02-27T06:54:59.357794+09:00",
      "usdt_kimp": 1.4531,
      "gold_kimp": -0.1257
    },
    {
      "time": "2026-02-27T07:34:42.809391+09:00",
      "usdt_kimp": 1.3831,
      "gold_kimp": -0.1257
    },
    {
      "time": "2026-02-27T08:05:31.537795+09:00",
      "usdt_kimp": 1.3831,
      "gold_kimp": -0.1023
    },
    {
      "time": "2026-02-27T08:45:44.472857+09:00",
      "usdt_kimp": 1.3831,
      "gold_kimp": -0.1547
    },
    {
      "time": "2026-02-27T11:06:05.966235+09:00",
      "usdt_kimp": 1.2528,
      "gold_kimp": 0.2945
    }
  ],
  "last_alert": {}
}